lanmonitor/__init__.py
lanmonitor/apt_upgrade_history_plugin.py
lanmonitor/dd_wrt_age_plugin.py
lanmonitor/freemem_plugin.py
lanmonitor/freespace_plugin.py
lanmonitor/fsactivity_plugin.py
lanmonitor/globvars.py
lanmonitor/interface_plugin.py
lanmonitor/lanmonfuncs.py
lanmonitor/lanmonitor.py
lanmonitor/pinghost_plugin.py
lanmonitor/process_plugin.py
lanmonitor/selinux_plugin.py
lanmonitor/service_plugin.py
lanmonitor/stock_notif.py
lanmonitor/webpage_plugin.py
lanmonitor/yum_update_history_plugin.py
lanmonitor/deployment_files/creds_SMTP
lanmonitor/deployment_files/lanmonitor.cfg
lanmonitor/deployment_files/lanmonitor.service
lanmonitor-4.0.1.dist-info/licenses/LICENSE
lanmonitor-4.0.1.dist-info/METADATA
lanmonitor-4.0.1.dist-info/WHEEL
lanmonitor-4.0.1.dist-info/entry_points.txt
lanmonitor-4.0.1.dist-info/top_level.txt
lanmonitor-4.0.1.dist-info/RECORD
