Metadata-Version: 2.4
Name: lanmonitor
Version: 4.0.1
Summary: Monitor the state of services, processes, web pages, file system, etc. on your server and LAN
Author-email: Chris Nelson <github@cjnaz.com>
License-Expression: MIT
Project-URL: repository, https://github.com/cjnaz/lanmonitor
Keywords: cjnaz,lan,monitor
Classifier: Programming Language :: Python :: 3
Classifier: Topic :: System :: Monitoring
Classifier: Topic :: System :: Networking :: Monitoring
Requires-Python: >=3.9
License-File: LICENSE
Requires-Dist: cjnfuncs>=3.0.1
Requires-Dist: asyncssh>=2.21.0
Requires-Dist: invoke>=2.2.0
Dynamic: license-file
